gateloop_transformer/__init__.py
gateloop_transformer/associative_scan.py
gateloop_transformer/gateloop_transformer.py
gateloop_transformer/gateloop_transformer_jax.py
gateloop_transformer/simplified_gate_loop.py
gateloop_transformer-0.2.5.dist-info/LICENSE
gateloop_transformer-0.2.5.dist-info/METADATA
gateloop_transformer-0.2.5.dist-info/WHEEL
gateloop_transformer-0.2.5.dist-info/top_level.txt
gateloop_transformer-0.2.5.dist-info/RECORD
